{
  "hints": [
    { "left": "让人感动", "right": "让人尴尬", "category": "情感与氛围" },
    { "left": "浪漫的", "right": "油腻的", "category": "情感与氛围" },
    { "left": "温馨", "right": "恐怖", "category": "情感与氛围" },
    { "left": "治愈系", "right": "致郁系", "category": "情感与氛围" },
    { "left": "开心", "right": "难过", "category": "情感与氛围" },
    { "left": "乐观", "right": "悲观", "category": "情感与氛围" },
    { "left": "甜", "right": "苦", "category": "情感与氛围" },
    { "left": "可爱的", "right": "吓人的", "category": "情感与氛围" },
    { "left": "有趣的", "right": "无聊的", "category": "情感与氛围" },

    { "left": "土味", "right": "高级感", "category": "审美与风格" },
    { "left": "极简风", "right": "繁复风", "category": "审美与风格" },
    { "left": "赛博朋克", "right": "田园牧歌", "category": "审美与风格" },
    { "left": "蒸汽朋克", "right": "未来科幻", "category": "审美与风格" },
    { "left": "暗黑系", "right": "小清新", "category": "审美与风格" },
    { "left": "对称", "right": "不对称", "category": "审美与风格" },
    { "left": "明亮", "right": "昏暗", "category": "审美与风格" },

    { "left": "社恐必备", "right": "社牛必备", "category": "社交与文化" },
    { "left": "独处", "right": "社交", "category": "社交与文化" },
    { "left": "沉默", "right": "表达", "category": "社交与文化" },
    { "left": "高调", "right": "低调", "category": "社交与文化" },
    { "left": "流行的", "right": "小众的", "category": "社交与文化" },
    { "left": "网红款", "right": "老字号", "category": "社交与文化" },
    { "left": "网络热梗", "right": "文言雅词", "category": "社交与文化" },
    { "left": "常说的话", "right": "不常说的话", "category": "社交与文化" },

    { "left": "硬核", "right": "轻松", "category": "体验与难度" },
    { "left": "需要努力", "right": "轻而易举", "category": "体验与难度" },
    { "left": "简单", "right": "复杂", "category": "体验与难度" },
    { "left": "一学就会", "right": "十年如一日", "category": "体验与难度" },
    { "left": "新手友好", "right": "劝退神器", "category": "体验与难度" },
    { "left": "佛系玩家", "right": "肝帝必玩", "category": "体验与难度" },

    { "left": "便宜", "right": "昂贵", "category": "生活与消费" },
    { "left": "学生党最爱", "right": "中产标配", "category": "生活与消费" },
    { "left": "实用主义", "right": "为爱发电", "category": "生活与消费" },
    { "left": "有用", "right": "无用", "category": "生活与消费" },
    { "left": "好吃", "right": "难吃", "category": "生活与消费" },
    { "left": "米其林", "right": "深夜食堂", "category": "生活与消费" },
    { "left": "养生", "right": "放纵", "category": "生活与消费" },

    { "left": "古老的", "right": "现代的", "category": "时间与空间" },
    { "left": "传统", "right": "创新", "category": "时间与空间" },
    { "left": "历史", "right": "未来", "category": "时间与空间" },
    { "left": "童年回忆", "right": "Z世代专属", "category": "时间与空间" },
    { "left": "快", "right": "慢", "category": "时间与空间" },
    { "left": "迅速", "right": "缓慢", "category": "时间与空间" },
    { "left": "突发", "right": "持续", "category": "时间与空间" },
    { "left": "近", "right": "远", "category": "时间与空间" },
    { "left": "微观", "right": "宏观", "category": "时间与空间" },
    { "left": "在地的", "right": "全球的", "category": "时间与空间" },

    { "left": "冷", "right": "热", "category": "形态与特征" },
    { "left": "清凉", "right": "炽热", "category": "形态与特征" },
    { "left": "高", "right": "矮", "category": "形态与特征" },
    { "left": "重", "right": "轻", "category": "形态与特征" },
    { "left": "硬", "right": "软", "category": "形态与特征" },
    { "left": "粗糙", "right": "光滑", "category": "形态与特征" },
    { "left": "直线", "right": "曲线", "category": "形态与特征" },
    { "left": "圆滑", "right": "棱角分明", "category": "形态与特征" },
    { "left": "多", "right": "少", "category": "形态与特征" },
    { "left": "单一", "right": "多样", "category": "形态与特征" },
    { "left": "单调", "right": "丰富", "category": "形态与特征" },
    { "left": "集中", "right": "分散", "category": "形态与特征" },

    { "left": "理性", "right": "感性", "category": "认知与思维" },
    { "left": "主观", "right": "客观", "category": "认知与思维" },
    { "left": "情绪化", "right": "理性思考", "category": "认知与思维" },
    { "left": "抽象", "right": "具体", "category": "认知与思维" },
    { "left": "清晰", "right": "模糊", "category": "认知与思维" },
    { "left": "深意", "right": "无意义", "category": "认知与思维" },
    { "left": "直觉", "right": "逻辑", "category": "认知与思维" },
    { "left": "浪漫主义", "right": "现实主义", "category": "认知与思维" },

    { "left": "现实中的", "right": "幻想中的", "category": "性质与状态" },
    { "left": "真实", "right": "虚构", "category": "性质与状态" },
    { "left": "现实", "right": "超现实", "category": "性质与状态" },
    { "left": "自然", "right": "人工", "category": "性质与状态" },
    { "left": "生物", "right": "机械", "category": "性质与状态" },
    { "left": "童话", "right": "纪实", "category": "性质与状态" },
    { "left": "安静", "right": "吵闹", "category": "性质与状态" },
    { "left": "无声", "right": "震耳欲聋", "category": "性质与状态" },
    { "left": "强", "right": "弱", "category": "性质与状态" },

    { "left": "保守", "right": "开放", "category": "态度与价值" },
    { "left": "谨慎", "right": "冒险", "category": "态度与价值" },
    { "left": "无害", "right": "危险", "category": "态度与价值" },
    { "left": "不可能的", "right": "必然的", "category": "态度与价值" },
    { "left": "一次性", "right": "永久", "category": "态度与价值" },
    { "left": "干预", "right": "自然生长", "category": "态度与价值" },
    { "left": "儿童喜欢", "right": "成人喜欢", "category": "态度与价值" },

    { "left": "地心引力", "right": "太空漂浮", "category": "创意与特殊" },
    { "left": "爆炸", "right": "蒸发", "category": "创意与特殊" },
    { "left": "休眠", "right": "爆发", "category": "创意与特殊" },
    { "left": "白日梦", "right": "噩梦", "category": "创意与特殊" },
    { "left": "蜜糖", "right": "砒霜", "category": "创意与特殊" },
    { "left": "刚需", "right": "智商税", "category": "创意与特殊" },
    { "left": "YYDS", "right": "DDDD", "category": "创意与特殊" },
    { "left": "emo了", "right": "起飞了", "category": "创意与特殊" },
    { "left": "很抽象", "right": "很具象", "category": "创意与特殊" },
    { "left": "纯纯牛马", "right": "绝世高手", "category": "创意与特殊" }
  ]
}
